MANIFEST.in
requirements.pip
setup.py
kruxstatsd/__init__.py
kruxstatsd/client.py
kruxstatsd/tests.py
kruxstatsd.egg-info/PKG-INFO
kruxstatsd.egg-info/SOURCES.txt
kruxstatsd.egg-info/dependency_links.txt
kruxstatsd.egg-info/requires.txt
kruxstatsd.egg-info/top_level.txt