Metadata-Version: 1.0
Name: kruxstatsd
Version: 0.2.2
Summary: Wrapper around pystatsd with automatic namespacing
Home-page: https://github.com/krux/python-kruxstatsd
Author: Paul Lathrop
Author-email: paul@krux.com
License: MIT
Download-URL: https://github.com/krux/python-kruxstatsd/tarball/release/0.2.2
Platform: UNKNOWN
